{
  "kind": "collectionType",
  "collectionName": "projects",
  "info": {
    "singularName": "project",
    "pluralName": "projects",
    "displayName": "Project",
    "description": ""
  },
  "options": {
    "draftAndPublish": true
  },
  "pluginOptions": {
    "i18n": {
      "localized": true
    }
  },
  "attributes": {
    "name": {
      "pluginOptions": {
        "i18n": {
          "localized": true
        }
      },
      "type": "string"
    },
    "service": {
      "type": "relation",
      "relation": "manyToOne",
      "target": "api::service.service",
      "inversedBy": "projects"
    },
    "technology": {
      "type": "relation",
      "relation": "manyToOne",
      "target": "api::technology.technology",
      "inversedBy": "projects"
    },
    "gallery": {
      "type": "media",
      "multiple": true,
      "required": false,
      "allowedTypes": [
        "images",
        "videos"
      ],
      "pluginOptions": {
        "i18n": {
          "localized": true
        }
      }
    },
    "thumbnail": {
      "type": "media",
      "multiple": false,
      "required": false,
      "allowedTypes": [
        "images"
      ],
      "pluginOptions": {
        "i18n": {
          "localized": true
        }
      }
    },
    "slug": {
      "pluginOptions": {
        "i18n": {
          "localized": true
        }
      },
      "type": "uid",
      "targetField": "name"
    }
  }
}
